{
  "categories": [
    {
      "id": "Friendlies Clubs",
      "name": "Friendlies Clubs",
      "imageUrl": "https://cdn.footystats.org/img/competitions/international-club-friendlies-1.png",
      "color": "#DC143C"
    },
    {
      "id": "Africa Cup of Nations - Women",
      "name": "Africa Cup of Nations - Women",
      "imageUrl": "https://upload.wikimedia.org/wikipedia/en/5/58/WAFCON_%28logo%29.png",
      "color": "#DC143C"
    }
    
  ],
  "matches": [
    {
      "match_id": 101,
      "status": "UPCOMING",
      "category_id": "Friendlies Clubs",
      "competition_name": "UEFA Champions League",
      "home_team": {
        "name": "Bayern München II",
        "logo_url": "https://media-sport.b-cdn.net/football/teams/4674.png"
      },
      "away_team": {
        "name": "SG Sonnenhof Grossaspach",
        "logo_url": "https://media-sport.b-cdn.net/football/teams/1317.png"
      },
      "streams": [
        "https://5nhp186eg31fofnc.api-redeem-coupon.click/v3/director/VE1MjVhMzNjZTkxZTdkLWRmZGItMWM4NC03Y2Q3LWU2NjQyMWU5/master.m3u8?auth_key=1752443752-ef20e755b3aff751ca30fe704842e500-00000000000000000000000000000000-9108234a704502ada6f0a53a92c1c89f"
      ]
    },
    {
      "match_id": 102,
      "status": "Live",
      "category_id": "Africa Cup of Nations - Women",
      "competition_name": "Africa Cup of Nations",
      "home_team": {
        "name": "Nigeria W",
        "logo_url": "https://media-sport.b-cdn.net/football/teams/1730.png"
      },
      "away_team": {
        "name": "Zambia W",
        "logo_url": "https://media-sport.b-cdn.net/football/teams/15584.png"
      },
      "streams": [
        "https://yfkijlwj1wm320xr.youaresoselfish.online/v3/director/VE1ZGIyMWQzMDE2MGFiLWUwNDktMzBjNC1kNjUyLTljMWEzNzFi/master.m3u8?auth_key=1752853982-e2060d5847aa316ff94d98a516c8f8ff-00000000000000000000000000000000-93abc7e6c3026de66a6850d8865ffdfc"
      ]
    }
   
 
   
  ]
}
